{
    "id": "7A706BCB-DAF2-49C0-B770-CE2DB484205D",
    "name": "InstallTopshelfService",
    "friendlyName": "Install Topshelf Service",
    "description": "Installs a TopShelf service using the standard command line options for Topshelf 4.0.",
    "helpMarkDown": "Version: {{tokens.BuildNumber}} [More Information](https://github.com/jabbera/my-vsts-tasks)",
    "category": "Deploy",
    "visibility": [
        "Build",
        "Release"
    ],
    "author": "Michael Barry",
    "version": {
        "Major": "{{tokens.Major}}",
        "Minor": "{{tokens.Minor}}",
        "Patch": "{{tokens.Patch}}"
    },
    "minimumAgentVersion": "1.95.0",	
    "inputs": [
        {
            "name": "TopshelfExePaths",
            "type": "multiLine",
            "label": "Topshelf Exe Paths",
            "defaultValue": "",
            "required": true,
            "helpMarkDown": "Full path to topshelf executables. (Comma separated list)" 
        },
        {
            "name": "EnvironmentName",
            "type": "multiLine",
            "label": "Machines",
            "defaultValue": "",
            "required": true,
            "helpMarkDown": "Provide a comma separated list of machine IP addresses or FQDNs. <br>Eg: dbserver.fabrikam.com,192.168.12.34 <br>Or provide output variable of other tasks. Eg: $(variableName)"
        },
        {
            "name": "AdminUserName",
            "type": "string",
            "label": "Admin Login",
            "defaultValue": "",
            "required": true,
            "helpMarkDown": "Administrator login for the target machines."
        },
        {
            "name": "AdminPassword",
            "type": "string",
            "label": "Password",
            "defaultValue": "",
            "required": true,
            "helpMarkDown": "Password for administrator login for the target machines. <br>It can accept variable defined in Build/Release definitions as '$(passwordVariable)'. <br>You may mark variable type as 'secret' to secure it. "
        },
		{
            "name": "protocol",
            "type": "radio",
            "label": "Protocol",
            "required": true,
            "defaultValue": "Http",
            "options": {
                "Http": "HTTP",
                "Https": "HTTPS"
            },
            "helpMarkDown": "Select the network protocol to use for the WinRM connection with the machine(s). The default is HTTPS."
        },
        {
            "name": "TestCertificate",
            "type": "boolean",
            "label": "Test Certificate",
            "defaultValue": "true",
            "visibleRule": "protocol = Https",
            "required": false,
            "helpMarkDown": "Select the option to skip validating the authenticity of the machine's certificate from a trusted certification authority. The parameter is required for the WinRM HTTPS protocol."
        },
        {
            "name": "RunPowershellInParallel",
            "type": "boolean",
            "label": "Run PowerShell in Parallel",
            "defaultValue": "true",
            "required": false,
            "helpMarkDown": "Setting it to true will run the PowerShell scripts in parallel on the target machines."
        },
		{
            "name": "specialUser",
            "type": "radio",
            "label": "Special User",
            "required": true,
            "defaultValue": "custom",
            "options": {
                "custom": "Custom",
                "localsystem": "Local System",
                "localservice": "Local Service",
                "networkservice": "Network Service"
            },
            "helpMarkDown": "Select the network protocol to use for the WinRM connection with the machine(s). The default is HTTPS."
        },
        {
            "name": "ServiceUsername",
            "type": "string",
            "label": "Service Username",
            "defaultValue": "",
			"visibleRule": "specialUser = custom",
            "required": false,
            "helpMarkDown": "Username to run the service as."
        },
        {
            "name": "ServicePassword",
            "type": "string",
            "label": "Service Password",
            "defaultValue": "",
			"visibleRule": "specialUser = custom",
            "required": false,
            "helpMarkDown": "Password for the service account"
        },
        {
            "name": "InstanceName",
            "type": "string",
            "label": "Instance Name",
            "defaultValue": "",
            "required": false,
            "helpMarkDown": "An instance name if neccessary."
        },
		{
		  "name": "StartupType",
		  "type": "radio",
		  "label": "Service Startup Type",
		  "required": false,
		  "defaultValue": "default",
		  "options": {
			"default": "Default",
			"manual": "Manual",
			"autostart": "Automatic",
			"disabled": "Disabled"
		  },
		  "helpMarkDown": "Select the startup type for the service."
		},
        {
            "name": "UninstallFirst",
            "type": "boolean",
            "label": "UnInstall service first",
            "defaultValue": "true",
            "required": true,
            "helpMarkDown": "Check to uninstall the services before installation, effectivly resetting any manual changes. This will also stop services if running. (not reccomend as timeout it not controllable)"
        },
        {
            "name": "KillMmcTaskManager",
            "type": "boolean",
            "label": "Before uninstall kill all mmc\\taskmgr",
            "defaultValue": "false",
			"visibleRule": "UninstallFirst = true",
            "required": true,
            "helpMarkDown": "Check to make the task kill all open instances of mmc and taskmgr in an attempt to avoid the dreaded: The specified service has been marked for deletion. See: http://stackoverflow.com/questions/20561990/how-to-solve-the-specified-service-has-been-marked-for-deletion-error"
        }
    ],
    "instanceNameFormat": "Install a Topshelf Service: $(TopshelfExePaths)",
    "execution": {
        "PowerShell3": {
            "target": "$(currentDirectory)\\InstallTopshelfService.ps1",
            "argumentFormat": "",
            "workingDirectory": "$(currentDirectory)"
        }
    }
}